main.py
ngiab-0.0.2.dist-info/METADATA
ngiab-0.0.2.dist-info/WHEEL
ngiab-0.0.2.dist-info/entry_points.txt
ngiab-0.0.2.dist-info/top_level.txt
ngiab-0.0.2.dist-info/RECORD
