Metadata-Version: 2.4
Name: ngiab
Version: 0.0.2
Summary: A collection of tools to run NextGen In A Box (NGIAB)
Requires-Python: >=3.11
Requires-Dist: ngiab_data_preprocess
Requires-Dist: ngiab-cal
